devtrack_sdk/__init__.py
devtrack_sdk/__version__.py
devtrack_sdk/cli.py
devtrack_sdk/database.py
devtrack_sdk/django_middleware.py
devtrack_sdk/django_urls.py
devtrack_sdk/django_views.py
devtrack_sdk/controller/__init__.py
devtrack_sdk/controller/devtrack_routes.py
devtrack_sdk/dashboard/index.html
devtrack_sdk/dashboard/dist/index.html
devtrack_sdk/dashboard/dist/assets/index.Can607VC.js
devtrack_sdk/dashboard/dist/assets/index.D4pIqhp4.css
devtrack_sdk/management/__init__.py
devtrack_sdk/management/commands/__init__.py
devtrack_sdk/management/commands/devtrack_init.py
devtrack_sdk/management/commands/devtrack_reset.py
devtrack_sdk/management/commands/devtrack_stats.py
devtrack_sdk/middleware/__init__.py
devtrack_sdk/middleware/base.py
devtrack_sdk/middleware/extractor.py
devtrack_sdk-0.4.2.dist-info/licenses/LICENSE
devtrack_sdk-0.4.2.dist-info/METADATA
devtrack_sdk-0.4.2.dist-info/WHEEL
devtrack_sdk-0.4.2.dist-info/entry_points.txt
devtrack_sdk-0.4.2.dist-info/top_level.txt
devtrack_sdk-0.4.2.dist-info/RECORD
