Metadata-Version: 2.4
Name: devtrack-sdk
Version: 0.4.2
Summary: Middleware-based API analytics and observability tool for FastAPI and Django
Home-page: https://github.com/mahesh-solanke/devtrack-sdk
Author: Mahesh Solanke
Author-email: Mahesh Solanke <maheshsolanke69@gmail.com>
License: MIT
Project-URL: Homepage, https://github.com/mahesh-solanke/devtrack-sdk
Classifier: Development Status :: 4 - Beta
Classifier: Programming Language :: Python :: 3
Classifier: Framework :: FastAPI
Classifier: Framework :: Django
Classifier: License :: OSI Approved :: MIT License
Classifier: Operating System :: OS Independent
Requires-Python: >=3.10
License-File: LICENSE
Requires-Dist: fastapi>=0.90
Requires-Dist: django>=4.0.0
Requires-Dist: httpx>=0.24
Requires-Dist: starlette>=0.22
Requires-Dist: rich>=13.3
Requires-Dist: typer>=0.9
Requires-Dist: duckdb>=1.1.0
Dynamic: author
Dynamic: home-page
Dynamic: license-file
Dynamic: requires-python
